replapiit_python_parser/__init__.py
replapiit_python_parser/core.py
replapiit_python_parser-0.0.2.dist-info/METADATA
replapiit_python_parser-0.0.2.dist-info/WHEEL
replapiit_python_parser-0.0.2.dist-info/top_level.txt
replapiit_python_parser-0.0.2.dist-info/zip-safe
replapiit_python_parser-0.0.2.dist-info/RECORD
